MANIFEST.in
README.md
setup.py
django_plugshop.egg-info/PKG-INFO
django_plugshop.egg-info/SOURCES.txt
django_plugshop.egg-info/dependency_links.txt
django_plugshop.egg-info/not-zip-safe
django_plugshop.egg-info/requires.txt
django_plugshop.egg-info/top_level.txt
plugshop/__init__.py
plugshop/admin.py
plugshop/cart.py
plugshop/exceptions.py
plugshop/forms.py
plugshop/middleware.py
plugshop/settings.py
plugshop/signals.py
plugshop/urls.py
plugshop/utils.py
plugshop/views.py
plugshop/locale/ru/LC_MESSAGES/django.mo
plugshop/locale/ru/LC_MESSAGES/django.po
plugshop/models/__init__.py
plugshop/models/category.py
plugshop/models/order.py
plugshop/models/order_products.py
plugshop/models/product.py
plugshop/templates/admin/category/change_list.html
plugshop/templates/admin/product/change_list.html
plugshop/templates/plugshop/_cart.html
plugshop/templates/plugshop/base.html
plugshop/templates/plugshop/cart.html
plugshop/templates/plugshop/category_detail.html
plugshop/templates/plugshop/category_list.html
plugshop/templates/plugshop/category_path.html
plugshop/templates/plugshop/order_detail.html
plugshop/templates/plugshop/order_form.html
plugshop/templates/plugshop/product_detail.html
plugshop/templates/plugshop/product_list.html
plugshop/templates/plugshop/email/order.html
plugshop/templates/plugshop/email/order_admin.html
plugshop/templates/plugshop/email/order_user.html
plugshop/templates/plugshop/tags/action.html
plugshop/templatetags/__init__.py
plugshop/templatetags/plugshop.py