Metadata-Version: 1.0
Name: django-plugshop
Version: 0.3.2
Summary: A small shop for Django Framework
Home-page: https://github.com/ChillyBwoy/django-plugshop
Author: Eugene Cheltsov
Author-email: chill.icp@gmail.com
License: BSD
Keywords: plugshop
Platform: OS Independent
Classifier: Environment :: Web Environment
Classifier: Framework :: Django
Classifier: Intended Audience :: Developers
Classifier: License :: OSI Approved :: BSD License
Classifier: Operating System :: OS Independent
Classifier: Programming Language :: Python
Classifier: Topic :: Software Development :: Libraries :: Application Frameworks
